{"otherData": {},"traceEvents":[{"cat":"function","dur":133,"name":"Contouring Update","ph":"X","pid":0,"tid":2700952355,"ts":1758879824255950},{"cat":"function","dur":3,"name":"Initializing Obstacles in Environment","ph":"X","pid":0,"tid":2700952355,"ts":1758879824256215},{"cat":"function","dur":3,"name":"Setting goals","ph":"X","pid":0,"tid":2700952355,"ts":1758879824256228},{"cat":"function","dur":10744,"name":"PRM::Update","ph":"X","pid":0,"tid":2700952355,"ts":1758879824256240},{"cat":"function","dur":19109,"name":"Path Search","ph":"X","pid":0,"tid":2700952355,"ts":1758879824267017},{"cat":"function","dur":1,"name":"KeepTopologyDistinctPaths","ph":"X","pid":0,"tid":2700952355,"ts":1758879824286166},{"cat":"function","dur":18,"name":"Path Filtering","ph":"X","pid":0,"tid":2700952355,"ts":1758879824286159},{"cat":"function","dur":29977,"name":"GlobalGuidance::Update","ph":"X","pid":0,"tid":2700952355,"ts":1758879824256206},{"cat":"function","dur":30285,"name":"Update","ph":"X","pid":0,"tid":2700952355,"ts":1758879824255948},{"cat":"function","dur":17628,"name":"SetParameters","ph":"X","pid":0,"tid":2700952355,"ts":1758879824286247},{"cat":"function","dur":0,"name":"Guidance Constraints: Parallel Optimization","ph":"X","pid":0,"tid":2700952355,"ts":1758879824304076},{"cat":"function","dur":1,"name":"Guidance Constraints: Parallel Optimization","ph":"X","pid":0,"tid":3465970620,"ts":1758879824304076},{"cat":"function","dur":1,"name":"Guidance Constraints: Parallel Optimization","ph":"X","pid":0,"tid":1528412364,"ts":1758879824304501},{"cat":"function","dur":1,"name":"Guidance Constraints: Parallel Optimization","ph":"X","pid":0,"tid":3005658128,"ts":1758879824306893},{"cat":"function","dur":5832,"name":"Guidance Constraints: Parallel Optimization","ph":"X","pid":0,"tid":919817311,"ts":1758879824304076},{"cat":"function","dur":14,"name":"Decision","ph":"X","pid":0,"tid":2700952355,"ts":1758879824309960},{"cat":"function","dur":5938,"name":"optimize","ph":"X","pid":0,"tid":2700952355,"ts":1758879824304046},{"cat":"function","dur":5947,"name":"Optimization","ph":"X","pid":0,"tid":2700952355,"ts":1758879824304043},{"cat":"function","dur":58822,"name":"Planning","ph":"X","pid":0,"tid":2700952355,"ts":1758879824251171},{"cat":"function","dur":28,"name":"/jackal2_PublishCurrentTrajectory","ph":"X","pid":0,"tid":2700952355,"ts":1758879824310177},{"cat":"function","dur":13430,"name":"Contouring::Visualize","ph":"X","pid":0,"tid":2700952355,"ts":1758879824310220},{"cat":"function","dur":4260,"name":"GlobalGuidance::Visualize","ph":"X","pid":0,"tid":2700952355,"ts":1758879824323682},{"cat":"function","dur":4897,"name":"GuidanceConstraints::Visualize","ph":"X","pid":0,"tid":2700952355,"ts":1758879824323671},{"cat":"function","dur":21767,"name":"Planner::Visualize","ph":"X","pid":0,"tid":2700952355,"ts":1758879824310217},{"cat":"function","dur":82513,"name":"/jackal2_planningLoop","ph":"X","pid":0,"tid":2700952355,"ts":1758879824249975},{"cat":"function","dur":141,"name":"/jackal2_ObstacleCallback","ph":"X","pid":0,"tid":2700952355,"ts":1758879824332700},{"cat":"function","dur":69,"name":"Contouring Update","ph":"X","pid":0,"tid":2700952355,"ts":1758879824334588},{"cat":"function","dur":4,"name":"Initializing Obstacles in Environment","ph":"X","pid":0,"tid":2700952355,"ts":1758879824335188},{"cat":"function","dur":7,"name":"Setting goals","ph":"X","pid":0,"tid":2700952355,"ts":1758879824335205},{"cat":"function","dur":10333,"name":"PRM::Update","ph":"X","pid":0,"tid":2700952355,"ts":1758879824335217},{"cat":"function","dur":4970,"name":"Path Search","ph":"X","pid":0,"tid":2700952355,"ts":1758879824345588},{"cat":"function","dur":1,"name":"KeepTopologyDistinctPaths","ph":"X","pid":0,"tid":2700952355,"ts":1758879824350616},{"cat":"function","dur":12,"name":"Path Filtering","ph":"X","pid":0,"tid":2700952355,"ts":1758879824350615},{"cat":"function","dur":15447,"name":"GlobalGuidance::Update","ph":"X","pid":0,"tid":2700952355,"ts":1758879824335185},{"cat":"function","dur":16090,"name":"Update","ph":"X","pid":0,"tid":2700952355,"ts":1758879824334587},{"cat":"function","dur":1488,"name":"SetParameters","ph":"X","pid":0,"tid":2700952355,"ts":1758879824350724},{"cat":"function","dur":0,"name":"Guidance Constraints: Parallel Optimization","ph":"X","pid":0,"tid":2700952355,"ts":1758879824352331},{"cat":"function","dur":0,"name":"Guidance Constraints: Parallel Optimization","ph":"X","pid":0,"tid":3465970620,"ts":1758879824352769},{"cat":"function","dur":0,"name":"Guidance Constraints: Parallel Optimization","ph":"X","pid":0,"tid":3005658128,"ts":1758879824352331},{"cat":"function","dur":0,"name":"Guidance Constraints: Parallel Optimization","ph":"X","pid":0,"tid":1528412364,"ts":1758879824352331},{"cat":"function","dur":22127,"name":"Guidance Constraints: Parallel Optimization","ph":"X","pid":0,"tid":919817311,"ts":1758879824352331},{"cat":"function","dur":10,"name":"Decision","ph":"X","pid":0,"tid":2700952355,"ts":1758879824378178},{"cat":"function","dur":25890,"name":"optimize","ph":"X","pid":0,"tid":2700952355,"ts":1758879824352322},{"cat":"function","dur":25898,"name":"Optimization","ph":"X","pid":0,"tid":2700952355,"ts":1758879824352320},{"cat":"function","dur":44352,"name":"Planning","ph":"X","pid":0,"tid":2700952355,"ts":1758879824333869},{"cat":"function","dur":20,"name":"/jackal2_PublishCurrentTrajectory","ph":"X","pid":0,"tid":2700952355,"ts":1758879824378435},{"cat":"function","dur":59,"name":"Contouring::Visualize","ph":"X","pid":0,"tid":2700952355,"ts":1758879824378471}